mqi/api.py
mqi/responseClass.py
mqi_sspd_api-1.2.0.dist-info/METADATA
mqi_sspd_api-1.2.0.dist-info/WHEEL
mqi_sspd_api-1.2.0.dist-info/licenses/LICENSE
mqi_sspd_api-1.2.0.dist-info/RECORD
