Metadata-Version: 2.4
Name: mqi_sspd_api
Version: 1.2.0
Summary: This is the official API of the MQI biasing box
Project-URL: Homepage, https://github.com/MQI-Software/mqi-api
Project-URL: Issues, https://github.com/MQI-Software/mqi-api/issues
Author-email: Matthias Wimmer <matthias.wimmer@munich-quantum-instruments.com>
License-File: LICENSE
Classifier: License :: OSI Approved :: MIT License
Classifier: Operating System :: OS Independent
Classifier: Programming Language :: Python :: 3
Requires-Python: >=3.0
Requires-Dist: rel
Requires-Dist: websocket-client
